copyclip/__init__.py
copyclip/main.py
copyclip-0.1.2.dist-info/METADATA
copyclip-0.1.2.dist-info/WHEEL
copyclip-0.1.2.dist-info/entry_points.txt
copyclip-0.1.2.dist-info/top_level.txt
copyclip-0.1.2.dist-info/RECORD
