Metadata-Version: 2.1
Name: copyclip
Version: 0.1.2
Summary: A CLI tool to copy code files from a directory to the clipboard
Home-page: https://github.com/somz22/copyclip
Author: Somil Jain
Author-email: somiljain9999@gmail.com
Classifier: Development Status :: 3 - Alpha
Classifier: Intended Audience :: Developers
Classifier: Topic :: Software Development :: Libraries :: Python Modules
Classifier: License :: OSI Approved :: MIT License
Classifier: Programming Language :: Python :: 3
Classifier: Programming Language :: Python :: 3.6
Classifier: Programming Language :: Python :: 3.7
Classifier: Programming Language :: Python :: 3.8
Classifier: Programming Language :: Python :: 3.9
Classifier: Operating System :: OS Independent
Requires-Python: >=3.6
Requires-Dist: pyperclip >=1.8.0
